bangumi/__init__.py
bangumi/api_endpoints.py
bangumi/client.py
bangumi/collection.py
bangumi/entity.py
bangumi/enum.py
bangumi/timeline.py
bangumi_data/__init__.py
bangumi_data/data.py
bangumi_data/entity.py
bangumi_recovery.py
timeline/__init__.py
timeline/api_endpoints.py
timeline/client.py
timeline/timeline.py
web/__init__.py
web/main_web.py
web/static/index.html
bangumi_recovery-0.3.1.dist-info/LICENCE
bangumi_recovery-0.3.1.dist-info/METADATA
bangumi_recovery-0.3.1.dist-info/WHEEL
bangumi_recovery-0.3.1.dist-info/entry_points.txt
bangumi_recovery-0.3.1.dist-info/RECORD
