Metadata-Version: 2.3
Name: bangumi_recovery
Version: 0.3.1
Summary: A tool for migrate bangumi tool
License: AGPL-3.0
Author: hx
Author-email: im@bgzo.cc
Requires-Python: >=3.12
Classifier: License :: OSI Approved :: GNU Affero General Public License v3
Classifier: Programming Language :: Python :: 3
Classifier: Programming Language :: Python :: 3.12
Classifier: Programming Language :: Python :: 3.13
Requires-Dist: beautifulsoup4 (>=4.13.4,<4.14.0)
Requires-Dist: click (>=8.2.1,<9.0.0)
Requires-Dist: fastapi (>=0.116.1,<0.117.0)
Requires-Dist: requests (>=2.32.4,<2.33.0)
Requires-Dist: uvicorn (>=0.35.0,<0.36.0)
Project-URL: Repository, https://github.com/bGZo/playground/tree/2025/07/bangumi-recovery-scripts
